stolgo/__init__.py
stolgo/breakout.py
stolgo/candlestick.py
stolgo/common.py
stolgo/exception.py
stolgo/helper.py
stolgo/nasdaq.py
stolgo/request.py
stolgo/samco.py
stolgo/trend.py
stolgo-0.1.0.dist-info/LICENSE
stolgo-0.1.0.dist-info/METADATA
stolgo-0.1.0.dist-info/WHEEL
stolgo-0.1.0.dist-info/top_level.txt
stolgo-0.1.0.dist-info/RECORD
