Metadata-Version: 2.1
Name: stolgo
Version: 0.1.0
Summary: Utilities for the analysis of financial data
Home-page: UNKNOWN
Author: stolgo Developers
Author-email: stockalgos@gmail.com
License: MIT
Download-URL: https://github.com/stockalgo/stolgo/archive/v0.1.0.tar.gz
Project-URL: Organization, http://www.stolgo.com
Project-URL: Source, https://github.com/stockalgo/stolgo
Project-URL: Tracker, https://github.com/stockalgo/stolgo/issues
Keywords: candlestick-patterns-detection,price-action,algorithmic-trading-strategies,breakout-detection,algorithmic-trading-python,algo-trading-software,nasdaq-python-api,price-action-python-api
Platform: UNKNOWN
Classifier: Development Status :: 5 - Production/Stable
Classifier: Intended Audience :: Developers
Classifier: Topic :: Software Development :: Build Tools
Classifier: License :: OSI Approved :: MIT License
Classifier: Programming Language :: Python :: 3
Classifier: Programming Language :: Python :: 3.5
Classifier: Programming Language :: Python :: 3.6
Classifier: Programming Language :: Python :: 3.7
Classifier: Programming Language :: Python :: 3.8
Requires-Dist: requests
Requires-Dist: pandas
Requires-Dist: datetime
Requires-Dist: openpyxl
Requires-Dist: futures
Requires-Dist: beautifulsoup4
Requires-Dist: lxml
